binance/__init__.py
binance/client.py
binance/depthcache.py
binance/enums.py
binance/exceptions.py
binance/helpers.py
binance/websockets.py
python3_binance-0.7.2.dist-info/LICENSE
python3_binance-0.7.2.dist-info/METADATA
python3_binance-0.7.2.dist-info/WHEEL
python3_binance-0.7.2.dist-info/top_level.txt
python3_binance-0.7.2.dist-info/RECORD
